{"hash":"2811600f081004b4db755606ddc56d26463fd6f2","data":{"allBlogPost":{"pageInfo":{"totalPages":14,"currentPage":13,"totalItems":131},"edges":[{"node":{"path":"/about/03304ab4/","id":"03304ab4","name":"Ars Technica","domain":"arstechnica.com","latest_scan":{"grade":"B","timestamp":"2020-07-23T20:01:35.266278Z","hsts":false,"valid_https":true}}},{"node":{"path":"/about/f46f561c/","id":"f46f561c","name":"Andhra Jyothi","domain":"andhrajyothy.com","latest_scan":{"grade":"B","timestamp":"2020-07-23T20:01:25.531521Z","hsts":false,"valid_https":true}}},{"node":{"path":"/about/7d96978a/","id":"7d96978a","name":"Anandabazar","domain":"anandabazar.com","latest_scan":{"grade":"B","timestamp":"2020-07-23T20:01:12.982748Z","hsts":false,"valid_https":true}}},{"node":{"path":"/about/703d5d2c/","id":"703d5d2c","name":"ABC News","domain":"abcnews.go.com","latest_scan":{"grade":"B","timestamp":"2020-07-23T20:00:38.368898Z","hsts":false,"valid_https":true}}},{"node":{"path":"/about/98193964/","id":"98193964","name":"ABC.es","domain":"abc.es","latest_scan":{"grade":"B","timestamp":"2020-07-23T20:00:16.287833Z","hsts":false,"valid_https":true}}},{"node":{"path":"/about/e6d6ff48/","id":"e6d6ff48","name":"SHINE","domain":"shine.cn","latest_scan":{"grade":"C","timestamp":"2020-07-23T20:13:23.785437Z","hsts":false,"valid_https":true}}},{"node":{"path":"/about/80095a74/","id":"80095a74","name":"Global Times","domain":"globaltimes.cn","latest_scan":{"grade":"C","timestamp":"2020-07-23T20:07:05.671522Z","hsts":false,"valid_https":true}}},{"node":{"path":"/about/052a32aa/","id":"052a32aa","name":"Drudge Report","domain":"drudgereport.com","latest_scan":{"grade":"C","timestamp":"2020-07-23T20:05:01.066454Z","hsts":true,"valid_https":true}}},{"node":{"path":"/about/7b225bfc/","id":"7b225bfc","name":"Xinhua News Agency","domain":"xinhuanet.com","latest_scan":{"grade":"F","timestamp":"2020-07-23T20:20:15.598141Z","hsts":false,"valid_https":false}}},{"node":{"path":"/about/2b93e62a/","id":"2b93e62a","name":"U.S. News & World Report","domain":"usnews.com","latest_scan":{"grade":"F","timestamp":"2020-07-23T20:18:35.460521Z","hsts":false,"valid_https":false}}}]}},"context":{}}